singlebase/__init__.py
singlebase/client.py
singlebase/lib.py
singlebase-0.1.1.dist-info/LICENSE
singlebase-0.1.1.dist-info/METADATA
singlebase-0.1.1.dist-info/WHEEL
singlebase-0.1.1.dist-info/top_level.txt
singlebase-0.1.1.dist-info/RECORD
